MANIFEST.in
README.md
setup.cfg
setup.py
grapher/web/__init__.py
grapher/web/server.py
grapher/web/__pycache__/__init__.cpython-37.pyc
grapher/web/__pycache__/server.cpython-37.pyc
grapher/web/ui/3rdpartylicenses.txt
grapher/web/ui/favicon.ico
grapher/web/ui/index.html
grapher/web/ui/main-es2015.c0e522447c173252c3d3.js
grapher/web/ui/main-es5.c0e522447c173252c3d3.js
grapher/web/ui/polyfills-es2015.2987770fde9daa1d8a2e.js
grapher/web/ui/polyfills-es5.6696c533341b95a3d617.js
grapher/web/ui/runtime-es2015.edb2fcf2778e7bf1d426.js
grapher/web/ui/runtime-es5.edb2fcf2778e7bf1d426.js
grapher/web/ui/styles.4de92e7b73cd12f1d7a8.css
grapher_web.egg-info/PKG-INFO
grapher_web.egg-info/SOURCES.txt
grapher_web.egg-info/dependency_links.txt
grapher_web.egg-info/top_level.txt